keisukemiyamotopypi/__init__.py
keisukemiyamotopypi/main.py
keisukemiyamotopypi-0.3.0.dist-info/METADATA
keisukemiyamotopypi-0.3.0.dist-info/WHEEL
keisukemiyamotopypi-0.3.0.dist-info/top_level.txt
keisukemiyamotopypi-0.3.0.dist-info/RECORD
